{
  "collectionName": "components_location_details_location_details",
  "info": {
    "displayName": "Location Details",
    "icon": "pinMap",
    "description": ""
  },
  "options": {},
  "attributes": {
    "address": {
      "type": "string",
      "required": true
    },
    "city": {
      "type": "string",
      "required": true
    },
    "state": {
      "type": "enumeration",
      "enum": [
        "TN",
        "VA",
        "KY"
      ],
      "required": true
    },
    "zipcode": {
      "type": "biginteger",
      "max": "10",
      "min": "5",
      "required": true
    }
  }
}
